fastapi_code_samples/CustomAuth.py
fastapi_code_samples/SampleGenerator.py
fastapi_code_samples/__init__.py
fastapi_code_samples-0.0.2.dist-info/LICENSE
fastapi_code_samples-0.0.2.dist-info/METADATA
fastapi_code_samples-0.0.2.dist-info/WHEEL
fastapi_code_samples-0.0.2.dist-info/top_level.txt
fastapi_code_samples-0.0.2.dist-info/RECORD
